README.rst
setup.py
alibabacloud_dkms_transfer/__init__.py
alibabacloud_dkms_transfer/kms_transfer_acs_client.py
alibabacloud_dkms_transfer/handlers/__init__.py
alibabacloud_dkms_transfer/handlers/asymmetic_decrypt_transfer_handler.py
alibabacloud_dkms_transfer/handlers/asymmetic_encrypt_transfer_handler.py
alibabacloud_dkms_transfer/handlers/asymmetic_sign_transfer_handler.py
alibabacloud_dkms_transfer/handlers/asymmetic_verify_transfer_handler.py
alibabacloud_dkms_transfer/handlers/decrypt_transfer_handler.py
alibabacloud_dkms_transfer/handlers/encrypt_transfer_handler.py
alibabacloud_dkms_transfer/handlers/generate_data_key_transfer_handler.py
alibabacloud_dkms_transfer/handlers/generate_data_key_without_plaintext_transfer_handler.py
alibabacloud_dkms_transfer/handlers/get_public_key_transfer_handler.py
alibabacloud_dkms_transfer/handlers/get_secret_value_transfer_handler.py
alibabacloud_dkms_transfer/handlers/kms_transfer_handler.py
alibabacloud_dkms_transfer/utils/__init__.py
alibabacloud_dkms_transfer/utils/consts.py
alibabacloud_dkms_transfer/utils/kms_error_code_transfer_utils.py
alibabacloud_dkms_transfer_python2.egg-info/PKG-INFO
alibabacloud_dkms_transfer_python2.egg-info/SOURCES.txt
alibabacloud_dkms_transfer_python2.egg-info/dependency_links.txt
alibabacloud_dkms_transfer_python2.egg-info/requires.txt
alibabacloud_dkms_transfer_python2.egg-info/top_level.txt