Metadata-Version: 1.1
Name: alibabacloud-dkms-transfer-python2
Version: 0.0.2
Summary: Alibaba Cloud Dedicated KMS Transfer SDK for Python2
Home-page: https://github.com/aliyun/alibabacloud-dkms-transfer-python2-sdk
Author: Alibaba Cloud SDK
Author-email: sdk-team@alibabacloud.com
License: Apache License 2.0
Keywords: alibabacloud,dkms-transfer-sdk
Platform: any
Classifier: Development Status :: 4 - Beta
Classifier: Intended Audience :: Developers
Classifier: License :: OSI Approved :: Apache Software License
Classifier: Programming Language :: Python
Classifier: Programming Language :: Python :: 2
Classifier: Programming Language :: Python :: 2.7
Classifier: Topic :: Software Development
